README.md
setup.py
pydotdict/__init__.py
pydotdict/pydotdict.py
pydotdict/test_pydotdict.py
pydotdict.egg-info/PKG-INFO
pydotdict.egg-info/SOURCES.txt
pydotdict.egg-info/dependency_links.txt
pydotdict.egg-info/top_level.txt