Metadata-Version: 2.1
Name: pydotdict
Version: 3.3.11
Summary: Production ready Python 3 dictionary with dot style access
Home-page: https://github.com/
Author: PyDotDict
Author-email: pydotdict@protonmail.ch
License: UNKNOWN
Platform: UNKNOWN
Classifier: Operating System :: OS Independent
Classifier: License :: OSI Approved :: MIT License
Classifier: Programming Language :: Python :: 3
